fstrent_bkitup/__init__.py
fstrent_bkitup/core.py
fstrent_bkitup-0.1.4.dist-info/METADATA
fstrent_bkitup-0.1.4.dist-info/WHEEL
fstrent_bkitup-0.1.4.dist-info/licenses/LICENSE
fstrent_bkitup-0.1.4.dist-info/RECORD
