Metadata-Version: 2.4
Name: fstrent_bkitup
Version: 0.1.4
Summary: A utility for creating timestamped backups of Python scripts and projects
Project-URL: Homepage, https://github.com/wrm3/fstrent_bkitup
Project-URL: Issues, https://github.com/wrm3/fstrent_bkitup/issues
Author-email: Warren R Martel III <wrmartel3@gmail.com>
License: MIT License
License-File: LICENSE
Keywords: backup,development,utility
Classifier: License :: OSI Approved :: MIT License
Classifier: Operating System :: OS Independent
Classifier: Programming Language :: Python :: 3
Requires-Python: >=3.7
